druid/__init__.py
druid/cli.py
druid/crow.py
druid/exceptions.py
druid/pydfu.py
druid/repl.py
druid/server.py
monome_druid-1.1.6.dist-info/licenses/LICENSE
monome_druid-1.1.6.dist-info/METADATA
monome_druid-1.1.6.dist-info/WHEEL
monome_druid-1.1.6.dist-info/entry_points.txt
monome_druid-1.1.6.dist-info/top_level.txt
monome_druid-1.1.6.dist-info/RECORD
