Metadata-Version: 2.4
Name: monome-druid
Version: 1.1.6
Summary: Terminal interface for crow
Home-page: https://github.com/monome/druid
Author: monome
Author-email: bcrabtree@monome.org
Classifier: Programming Language :: Python :: 3
Classifier: License :: OSI Approved :: GNU General Public License v3 (GPLv3)
Classifier: Operating System :: OS Independent
Requires-Python: >=3.6
License-File: LICENSE
Requires-Dist: Click>=7.0
Requires-Dist: packaging
Requires-Dist: prompt-toolkit<3.0,>=2.0.10
Requires-Dist: pyserial>=3.4
Requires-Dist: pyusb
Requires-Dist: requests
Requires-Dist: websockets>=9.1
Requires-Dist: setuptools
Requires-Dist: setuptools_scm
Requires-Dist: setuptools_scm_git_archive
Provides-Extra: test
Requires-Dist: pylint; extra == "test"
Dynamic: author
Dynamic: author-email
Dynamic: classifier
Dynamic: description
Dynamic: description-content-type
Dynamic: home-page
Dynamic: license-file
Dynamic: provides-extra
Dynamic: requires-dist
Dynamic: requires-python
Dynamic: summary
